plonetheme.barceloneta-3.3.3-py3.13-nspkg.pth
plonetheme/barceloneta/__init__.py
plonetheme/barceloneta/configure.zcml
plonetheme/barceloneta/interfaces.py
plonetheme/barceloneta/profiles/default/metadata.xml
plonetheme/barceloneta/profiles/default/theme.xml
plonetheme/barceloneta/profiles/default/registry/tinymce.xml
plonetheme/barceloneta/theme/backend.xml
plonetheme/barceloneta/theme/barceloneta-apple-touch-icon-114x114-precomposed.png
plonetheme/barceloneta/theme/barceloneta-apple-touch-icon-144x144-precomposed.png
plonetheme/barceloneta/theme/barceloneta-apple-touch-icon-57x57-precomposed.png
plonetheme/barceloneta/theme/barceloneta-apple-touch-icon-72x72-precomposed.png
plonetheme/barceloneta/theme/barceloneta-apple-touch-icon-precomposed.png
plonetheme/barceloneta/theme/barceloneta-apple-touch-icon.png
plonetheme/barceloneta/theme/barceloneta-favicon.ico
plonetheme/barceloneta/theme/grid-col-marker.xml
plonetheme/barceloneta/theme/index.html
plonetheme/barceloneta/theme/manifest.cfg
plonetheme/barceloneta/theme/preview.png
plonetheme/barceloneta/theme/rules.xml
plonetheme/barceloneta/theme/css/barceloneta-toolbar.css
plonetheme/barceloneta/theme/css/barceloneta-toolbar.css.map
plonetheme/barceloneta/theme/css/barceloneta-toolbar.min.css
plonetheme/barceloneta/theme/css/barceloneta-toolbar.min.css.map
plonetheme/barceloneta/theme/css/barceloneta.css
plonetheme/barceloneta/theme/css/barceloneta.css.map
plonetheme/barceloneta/theme/css/barceloneta.min.css
plonetheme/barceloneta/theme/css/barceloneta.min.css.map
plonetheme/barceloneta/theme/roboto/Apache License.txt
plonetheme/barceloneta/theme/roboto/README.rst
plonetheme/barceloneta/theme/roboto/generator_config.txt
plonetheme/barceloneta/theme/roboto/roboto-black.eot
plonetheme/barceloneta/theme/roboto/roboto-black.svg
plonetheme/barceloneta/theme/roboto/roboto-black.ttf
plonetheme/barceloneta/theme/roboto/roboto-black.woff
plonetheme/barceloneta/theme/roboto/roboto-black.woff2
plonetheme_barceloneta-3.3.3.dist-info/METADATA
plonetheme_barceloneta-3.3.3.dist-info/WHEEL
plonetheme_barceloneta-3.3.3.dist-info/entry_points.txt
plonetheme_barceloneta-3.3.3.dist-info/namespace_packages.txt
plonetheme_barceloneta-3.3.3.dist-info/top_level.txt
plonetheme_barceloneta-3.3.3.dist-info/RECORD
